{
	"$schema": "http://schema.management.azure.com/schemas/2015-01-01/deploymentTemplate.json#",
	"contentVersion": "1.0.0.0",
	"parameters": {
		"factoryName": {
			"type": "string",
			"metadata": "Data Factory name",
			"defaultValue": "DFanup"
		}
	},
	"variables": {
		"factoryId": "[concat('Microsoft.DataFactory/factories/', parameters('factoryName'))]"
	},
	"resources": [
		{
			"name": "[concat(parameters('factoryName'), '/DS_incre')]",
			"type": "Microsoft.DataFactory/factories/datasets",
			"apiVersion": "2018-06-01",
			"properties": {
				"linkedServiceName": {
					"referenceName": "AzureDataLakeStorage1",
					"type": "LinkedServiceReference"
				},
				"annotations": [],
				"type": "DelimitedText",
				"typeProperties": {
					"location": {
						"type": "AzureBlobFSLocation",
						"folderPath": "RAW",
						"fileSystem": "container1"
					},
					"columnDelimiter": ",",
					"escapeChar": "\\",
					"firstRowAsHeader": true,
					"quoteChar": "\""
				},
				"schema": [
					{
						"name": "Pregnancies",
						"type": "String"
					},
					{
						"name": "Glucose",
						"type": "String"
					},
					{
						"name": "BloodPressure",
						"type": "String"
					},
					{
						"name": "SkinThickness",
						"type": "String"
					},
					{
						"name": "Insulin",
						"type": "String"
					},
					{
						"name": "BMI",
						"type": "String"
					},
					{
						"name": "DiabetesPedigreeFunction",
						"type": "String"
					},
					{
						"name": "Age",
						"type": "String"
					},
					{
						"name": "Outcome",
						"type": "String"
					}
				]
			},
			"dependsOn": []
		},
		{
			"name": "[concat(parameters('factoryName'), '/DS_incre_parquet')]",
			"type": "Microsoft.DataFactory/factories/datasets",
			"apiVersion": "2018-06-01",
			"properties": {
				"linkedServiceName": {
					"referenceName": "AzureDataLakeStorage1",
					"type": "LinkedServiceReference"
				},
				"annotations": [],
				"type": "DelimitedText",
				"typeProperties": {
					"location": {
						"type": "AzureBlobFSLocation",
						"folderPath": "CLEANSED",
						"fileSystem": "container1"
					},
					"columnDelimiter": ",",
					"escapeChar": "\\",
					"firstRowAsHeader": true,
					"quoteChar": "\""
				},
				"schema": []
			},
			"dependsOn": []
		},
		{
			"name": "[concat(parameters('factoryName'), '/DS_rawParquetsink1')]",
			"type": "Microsoft.DataFactory/factories/datasets",
			"apiVersion": "2018-06-01",
			"properties": {
				"linkedServiceName": {
					"referenceName": "AzureDataLakeStorage1",
					"type": "LinkedServiceReference"
				},
				"annotations": [],
				"type": "Parquet",
				"typeProperties": {
					"location": {
						"type": "AzureBlobFSLocation",
						"fileName": "purchaseheader.parquet",
						"folderPath": "RAW/Rawparquet",
						"fileSystem": "container1"
					},
					"compressionCodec": "snappy"
				},
				"schema": []
			},
			"dependsOn": []
		},
		{
			"name": "[concat(parameters('factoryName'), '/DS_rawParquetsink2')]",
			"type": "Microsoft.DataFactory/factories/datasets",
			"apiVersion": "2018-06-01",
			"properties": {
				"linkedServiceName": {
					"referenceName": "AzureDataLakeStorage1",
					"type": "LinkedServiceReference"
				},
				"annotations": [],
				"type": "Parquet",
				"typeProperties": {
					"location": {
						"type": "AzureBlobFSLocation",
						"fileName": "purchaseorder.parquet",
						"folderPath": "RAW/Rawparquet",
						"fileSystem": "container1"
					},
					"compressionCodec": "snappy"
				},
				"schema": []
			},
			"dependsOn": []
		},
		{
			"name": "[concat(parameters('factoryName'), '/DS_rawcsvtocleansedparquet')]",
			"type": "Microsoft.DataFactory/factories/datasets",
			"apiVersion": "2018-06-01",
			"properties": {
				"linkedServiceName": {
					"referenceName": "AzureDataLakeStorage1",
					"type": "LinkedServiceReference"
				},
				"annotations": [],
				"type": "DelimitedText",
				"typeProperties": {
					"location": {
						"type": "AzureBlobFSLocation",
						"fileName": "purchaseorder.csv",
						"folderPath": "RAW",
						"fileSystem": "container1"
					},
					"columnDelimiter": ",",
					"escapeChar": "\\",
					"firstRowAsHeader": true,
					"nullValue": "EMAILNULL",
					"quoteChar": "\""
				},
				"schema": [
					{
						"name": "PurchaseOrderID",
						"type": "String"
					},
					{
						"name": "PurchaseOrderDetailID",
						"type": "String"
					},
					{
						"name": "DueDate",
						"type": "String"
					},
					{
						"name": "OrderQty",
						"type": "String"
					},
					{
						"name": "ProductID",
						"type": "String"
					},
					{
						"name": "UnitPrice",
						"type": "String"
					},
					{
						"name": "LineTotal",
						"type": "String"
					},
					{
						"name": "ReceivedQty",
						"type": "String"
					},
					{
						"name": "RejectedQty",
						"type": "String"
					},
					{
						"name": "StockedQty",
						"type": "String"
					},
					{
						"name": "ModifiedDate",
						"type": "String"
					}
				]
			},
			"dependsOn": []
		},
		{
			"name": "[concat(parameters('factoryName'), '/DS_restapisink')]",
			"type": "Microsoft.DataFactory/factories/datasets",
			"apiVersion": "2018-06-01",
			"properties": {
				"linkedServiceName": {
					"referenceName": "AzureDataLakeStorage1",
					"type": "LinkedServiceReference"
				},
				"annotations": [],
				"type": "DelimitedText",
				"typeProperties": {
					"location": {
						"type": "AzureBlobFSLocation",
						"folderPath": "RAW/RestApi/Sink",
						"fileSystem": "container1"
					},
					"columnDelimiter": ",",
					"escapeChar": "\\",
					"quoteChar": "\""
				},
				"schema": []
			},
			"dependsOn": []
		},
		{
			"name": "[concat(parameters('factoryName'), '/DS_sqldb')]",
			"type": "Microsoft.DataFactory/factories/datasets",
			"apiVersion": "2018-06-01",
			"properties": {
				"linkedServiceName": {
					"referenceName": "LS_Staging",
					"type": "LinkedServiceReference"
				},
				"annotations": [],
				"type": "AzureSqlTable",
				"schema": [],
				"typeProperties": {
					"schema": "dbo",
					"table": "Jsonstream"
				}
			},
			"dependsOn": []
		},
		{
			"name": "[concat(parameters('factoryName'), '/DS_streamRasbPiSource')]",
			"type": "Microsoft.DataFactory/factories/datasets",
			"apiVersion": "2018-06-01",
			"properties": {
				"linkedServiceName": {
					"referenceName": "LS_Cont2StreamADf",
					"type": "LinkedServiceReference"
				},
				"annotations": [],
				"type": "Json",
				"typeProperties": {
					"location": {
						"type": "AzureBlobFSLocation",
						"fileName": "0_823aef7406dd4a1c9cd79df58dbd3e50_1.json",
						"fileSystem": "container2stream"
					}
				},
				"schema": {
					"type": "object",
					"properties": {
						"messageId": {
							"type": "integer"
						},
						"deviceId": {
							"type": "string"
						},
						"temperature": {
							"type": "number"
						},
						"humidity": {
							"type": "number"
						},
						"EventProcessedUtcTime": {
							"type": "string"
						},
						"PartitionId": {
							"type": "integer"
						},
						"EventEnqueuedUtcTime": {
							"type": "string"
						},
						"IoTHub": {
							"type": "object",
							"properties": {
								"MessageId": {
									"type": "null"
								},
								"CorrelationId": {
									"type": "null"
								},
								"ConnectionDeviceId": {
									"type": "string"
								},
								"ConnectionDeviceGenerationId": {
									"type": "string"
								},
								"EnqueuedTime": {
									"type": "string"
								}
							}
						}
					}
				}
			},
			"dependsOn": []
		},
		{
			"name": "[concat(parameters('factoryName'), '/DelimitedText1')]",
			"type": "Microsoft.DataFactory/factories/datasets",
			"apiVersion": "2018-06-01",
			"properties": {
				"linkedServiceName": {
					"referenceName": "AzureDataLakeStorage2",
					"type": "LinkedServiceReference"
				},
				"annotations": [],
				"type": "DelimitedText",
				"typeProperties": {
					"location": {
						"type": "AzureBlobFSLocation",
						"fileName": "pract.csv",
						"fileSystem": "container1"
					},
					"columnDelimiter": ",",
					"escapeChar": "\\",
					"firstRowAsHeader": true,
					"quoteChar": "\""
				},
				"schema": [
					{
						"type": "String"
					},
					{
						"type": "String"
					},
					{
						"type": "String"
					}
				]
			},
			"dependsOn": []
		},
		{
			"name": "[concat(parameters('factoryName'), '/DelimitedText2')]",
			"type": "Microsoft.DataFactory/factories/datasets",
			"apiVersion": "2018-06-01",
			"properties": {
				"linkedServiceName": {
					"referenceName": "AzureDataLakeStorage1",
					"type": "LinkedServiceReference"
				},
				"annotations": [],
				"type": "DelimitedText",
				"typeProperties": {
					"location": {
						"type": "AzureBlobFSLocation",
						"fileName": "pract.csv",
						"folderPath": "current",
						"fileSystem": "trial"
					},
					"columnDelimiter": ",",
					"escapeChar": "\\",
					"firstRowAsHeader": true,
					"quoteChar": "\""
				},
				"schema": [
					{
						"name": "ID",
						"type": "String"
					},
					{
						"name": "Name",
						"type": "String"
					},
					{
						"name": "Salary",
						"type": "String"
					}
				]
			},
			"dependsOn": []
		},
		{
			"name": "[concat(parameters('factoryName'), '/DestinationDataset_a50')]",
			"type": "Microsoft.DataFactory/factories/datasets",
			"apiVersion": "2018-06-01",
			"properties": {
				"linkedServiceName": {
					"referenceName": "AzureDataLakeStorage3",
					"type": "LinkedServiceReference"
				},
				"annotations": [],
				"type": "Binary",
				"typeProperties": {
					"location": {
						"type": "AzureBlobFSLocation",
						"fileSystem": "destination"
					}
				}
			},
			"dependsOn": []
		},
		{
			"name": "[concat(parameters('factoryName'), '/DestinationDataset_g55')]",
			"type": "Microsoft.DataFactory/factories/datasets",
			"apiVersion": "2018-06-01",
			"properties": {
				"linkedServiceName": {
					"referenceName": "AzureDataLakeStorage3",
					"type": "LinkedServiceReference"
				},
				"annotations": [],
				"type": "Binary",
				"typeProperties": {
					"location": {
						"type": "AzureBlobFSLocation",
						"fileSystem": "destination"
					}
				}
			},
			"dependsOn": []
		},
		{
			"name": "[concat(parameters('factoryName'), '/DestinationDataset_mub')]",
			"type": "Microsoft.DataFactory/factories/datasets",
			"apiVersion": "2018-06-01",
			"properties": {
				"linkedServiceName": {
					"referenceName": "AzureDataLakeStorage3",
					"type": "LinkedServiceReference"
				},
				"annotations": [],
				"type": "Binary",
				"typeProperties": {
					"location": {
						"type": "AzureBlobFSLocation",
						"fileSystem": "destination"
					}
				}
			},
			"dependsOn": []
		},
		{
			"name": "[concat(parameters('factoryName'), '/DestinationDataset_ors')]",
			"type": "Microsoft.DataFactory/factories/datasets",
			"apiVersion": "2018-06-01",
			"properties": {
				"linkedServiceName": {
					"referenceName": "AzureDataLakeStorage3",
					"type": "LinkedServiceReference"
				},
				"annotations": [],
				"type": "Binary",
				"typeProperties": {
					"location": {
						"type": "AzureBlobFSLocation",
						"fileSystem": "destination"
					}
				}
			},
			"dependsOn": []
		},
		{
			"name": "[concat(parameters('factoryName'), '/DestinationDataset_sis')]",
			"type": "Microsoft.DataFactory/factories/datasets",
			"apiVersion": "2018-06-01",
			"properties": {
				"linkedServiceName": {
					"referenceName": "AzureDataLakeStorage5",
					"type": "LinkedServiceReference"
				},
				"annotations": [],
				"type": "Binary",
				"typeProperties": {
					"location": {
						"type": "AzureBlobFSLocation",
						"fileSystem": "destination"
					}
				}
			},
			"dependsOn": []
		},
		{
			"name": "[concat(parameters('factoryName'), '/FTP_Binary_source')]",
			"type": "Microsoft.DataFactory/factories/datasets",
			"apiVersion": "2018-06-01",
			"properties": {
				"linkedServiceName": {
					"referenceName": "FtpServer1",
					"type": "LinkedServiceReference"
				},
				"annotations": [],
				"type": "Binary",
				"typeProperties": {
					"location": {
						"type": "FtpServerLocation",
						"fileName": "REP1856.csv",
						"folderPath": "reda"
					}
				}
			},
			"dependsOn": []
		},
		{
			"name": "[concat(parameters('factoryName'), '/SourceDataset_a50')]",
			"type": "Microsoft.DataFactory/factories/datasets",
			"apiVersion": "2018-06-01",
			"properties": {
				"linkedServiceName": {
					"referenceName": "AzureDataLakeStorage3",
					"type": "LinkedServiceReference"
				},
				"annotations": [],
				"type": "Binary",
				"typeProperties": {
					"location": {
						"type": "AzureBlobFSLocation",
						"fileSystem": "source"
					}
				}
			},
			"dependsOn": []
		},
		{
			"name": "[concat(parameters('factoryName'), '/SourceDataset_g55')]",
			"type": "Microsoft.DataFactory/factories/datasets",
			"apiVersion": "2018-06-01",
			"properties": {
				"linkedServiceName": {
					"referenceName": "AzureDataLakeStorage3",
					"type": "LinkedServiceReference"
				},
				"annotations": [],
				"type": "Binary",
				"typeProperties": {
					"location": {
						"type": "AzureBlobFSLocation",
						"fileSystem": "source"
					}
				}
			},
			"dependsOn": []
		},
		{
			"name": "[concat(parameters('factoryName'), '/SourceDataset_mub')]",
			"type": "Microsoft.DataFactory/factories/datasets",
			"apiVersion": "2018-06-01",
			"properties": {
				"linkedServiceName": {
					"referenceName": "AzureDataLakeStorage3",
					"type": "LinkedServiceReference"
				},
				"annotations": [],
				"type": "Binary",
				"typeProperties": {
					"location": {
						"type": "AzureBlobFSLocation",
						"fileSystem": "source"
					}
				}
			},
			"dependsOn": []
		},
		{
			"name": "[concat(parameters('factoryName'), '/SourceDataset_ors')]",
			"type": "Microsoft.DataFactory/factories/datasets",
			"apiVersion": "2018-06-01",
			"properties": {
				"linkedServiceName": {
					"referenceName": "AzureDataLakeStorage3",
					"type": "LinkedServiceReference"
				},
				"annotations": [],
				"type": "Binary",
				"typeProperties": {
					"location": {
						"type": "AzureBlobFSLocation",
						"fileSystem": "source"
					}
				}
			},
			"dependsOn": []
		}
	]
}